personalab/__init__.py
personalab/config.py
personalab/config/__init__.py
personalab/db/__init__.py
personalab/db/config.py
personalab/db/pg_storage.py
personalab/db/utils.py
personalab/llm/__init__.py
personalab/llm/anthropic_client.py
personalab/llm/base.py
personalab/llm/custom_client.py
personalab/llm/openai_client.py
personalab/memo/__init__.py
personalab/memo/embeddings.py
personalab/memo/manager.py
personalab/memo/models.py
personalab/memory/__init__.py
personalab/memory/base.py
personalab/memory/manager.py
personalab/memory/pipeline.py
personalab/persona/__init__.py
personalab/persona/persona.py
personalab/utils/__init__.py
personalab/utils/logging.py
personalab-0.1.3.dist-info/METADATA
personalab-0.1.3.dist-info/WHEEL
personalab-0.1.3.dist-info/entry_points.txt
personalab-0.1.3.dist-info/top_level.txt
personalab-0.1.3.dist-info/RECORD
