Metadata-Version: 2.1
Name: personalab
Version: 0.1.3
Summary: AI Memory and Conversation Management Framework - Simple as mem0, Powerful as PersonaLab
Author-email: PersonaLab Team <support@personalab.ai>
Project-URL: Homepage, https://github.com/NevaMind-AI/PersonaLab
Project-URL: Bug Tracker, https://github.com/NevaMind-AI/PersonaLab/issues
Project-URL: Documentation, https://github.com/NevaMind-AI/PersonaLab#readme
Keywords: ai,memory,conversation,llm,chatbot,persona,agent
Classifier: Development Status :: 4 - Beta
Classifier: Intended Audience :: Developers
Classifier: Operating System :: OS Independent
Classifier: Programming Language :: Python :: 3
Classifier: Programming Language :: Python :: 3.8
Classifier: Programming Language :: Python :: 3.9
Classifier: Programming Language :: Python :: 3.10
Classifier: Programming Language :: Python :: 3.11
Classifier: Programming Language :: Python :: 3.12
Requires-Python: >=3.8
Requires-Dist: requests>=2.31.0
Requires-Dist: python-dotenv>=0.19.0
Requires-Dist: json5>=0.9.0
Requires-Dist: openai>=1.60.0
Requires-Dist: httpx<0.28,>=0.23
Requires-Dist: pydantic>=2.7.5
Requires-Dist: starlette>=0.40.0
Requires-Dist: fastapi>=0.115.2
Provides-Extra: ai
Requires-Dist: openai>=1.60.0; extra == "ai"
Requires-Dist: sentence-transformers>=2.2.0; extra == "ai"
Provides-Extra: all
Requires-Dist: openai>=1.0.0; extra == "all"
Requires-Dist: sentence-transformers>=2.2.0; extra == "all"
Requires-Dist: anthropic>=0.7.0; extra == "all"
Requires-Dist: google-generativeai>=0.3.0; extra == "all"
Requires-Dist: cohere>=4.0.0; extra == "all"
Requires-Dist: boto3>=1.26.0; extra == "all"
Requires-Dist: together>=0.2.0; extra == "all"
Requires-Dist: replicate>=0.15.0; extra == "all"
Requires-Dist: transformers>=4.21.0; extra == "all"
Requires-Dist: torch>=1.12.0; extra == "all"
Requires-Dist: psycopg2-binary>=2.9.9; extra == "all"
Provides-Extra: database
Requires-Dist: psycopg2-binary>=2.9.9; extra == "database"
Provides-Extra: dev
Requires-Dist: pytest>=7.0; extra == "dev"
Requires-Dist: pytest-cov>=4.0; extra == "dev"
Requires-Dist: black>=22.0; extra == "dev"
Requires-Dist: flake8>=5.0; extra == "dev"
Requires-Dist: mypy>=1.0; extra == "dev"
Requires-Dist: pre-commit>=3.0; extra == "dev"
Requires-Dist: twine>=4.0; extra == "dev"
Requires-Dist: build>=0.10; extra == "dev"
Provides-Extra: llm
Requires-Dist: openai>=1.60.0; extra == "llm"
Requires-Dist: anthropic>=0.54.0; extra == "llm"
Requires-Dist: google-generativeai>=0.3.0; extra == "llm"
Requires-Dist: cohere>=4.0.0; extra == "llm"
Requires-Dist: boto3>=1.26.0; extra == "llm"
Requires-Dist: together>=0.2.0; extra == "llm"
Requires-Dist: replicate>=0.15.0; extra == "llm"
Provides-Extra: local
Requires-Dist: transformers>=4.21.0; extra == "local"
Requires-Dist: torch>=1.12.0; extra == "local"
Requires-Dist: sentence-transformers>=2.2.0; extra == "local"
